<?xml version="1.0"?>
<root>
    <!-- Survey 1 -->
    <Survey>
        <start_run>79</start_run>
        <end_run>177</end_run>
        <detector>RPD</detector>
        <x_pos>0.1542</x_pos>
        <y_pos>-0.489</y_pos>
        <z_pos>30.88</z_pos>
        <cos_x>0.01</cos_x>
        <cos_y>0.01</cos_y>
        <cos_z>0.01</cos_z>
    </Survey>
    <Survey>
        <start_run>79</start_run>
        <end_run>177</end_run>
        <detector>ZDC1</detector>
        <x_pos>0.14962478</x_pos>
        <y_pos>-0.1514125</y_pos>
        <z_pos>30.6650356</z_pos>
        <cos_x>0.01</cos_x>
        <cos_y>0.01</cos_y>
        <cos_z>0.01</cos_z>
    </Survey>
    <Survey>
        <start_run>79</start_run>
        <end_run>177</end_run>
        <detector>ZDC2</detector>
        <x_pos>0.14712496</x_pos>
        <y_pos>-0.14634221</y_pos>
        <z_pos>31.10573708</z_pos>
        <cos_x>0.01</cos_x>
        <cos_y>0.01</cos_y>
        <cos_z>0.01</cos_z>
    </Survey>
    <!-- Survey 2 -->
    <Survey>
        <start_run>190</start_run>
        <end_run>231</end_run>
        <detector>RPD</detector>
        <x_pos>1</x_pos>
        <y_pos>2</y_pos>
        <z_pos>3</z_pos>
        <cos_x>0.01</cos_x>
        <cos_y>0.01</cos_y>
        <cos_z>0.01</cos_z>
    </Survey>
    <Survey>
        <start_run>190</start_run>
        <end_run>231</end_run>
        <detector>ZDC1</detector>
        <x_pos>1</x_pos>
        <y_pos>2</y_pos>
        <z_pos>3</z_pos>
        <cos_x>0.01</cos_x>
        <cos_y>0.01</cos_y>
        <cos_z>0.01</cos_z>
    </Survey>
    <Survey>
        <start_run>190</start_run>
        <end_run>231</end_run>
        <detector>ZDC2</detector>
        <x_pos>1</x_pos>
        <y_pos>2</y_pos>
        <z_pos>3</z_pos>
        <cos_x>0.01</cos_x>
        <cos_y>0.01</cos_y>
        <cos_z>0.01</cos_z>
    </Survey>
	<!-- Survey 3 -->
    <Survey>
        <start_run>258</start_run>
        <end_run>413</end_run>
        <detector>RPD</detector>
        <x_pos>1</x_pos>
        <y_pos>2</y_pos>
        <z_pos>3</z_pos>
        <cos_x>0.01</cos_x>
        <cos_y>0.01</cos_y>
        <cos_z>0.01</cos_z>
    </Survey>
    <Survey>
        <start_run>258</start_run>
        <end_run>413</end_run>
        <detector>ZDC1</detector>
        <x_pos>-0.0185256339</x_pos>
        <y_pos>0.348166976</y_pos>
        <z_pos>30.6794095</z_pos>
        <cos_x>0.01</cos_x>
        <cos_y>0.01</cos_y>
        <cos_z>0.01</cos_z>
    </Survey>
    <Survey>
        <start_run>258</start_run>
        <end_run>413</end_run>
        <detector>ZDC2</detector>
        <x_pos>-0.0202770450</x_pos>
        <y_pos>0.347088779</y_pos>
        <z_pos>31.1316026</z_pos>
        <cos_x>0.01</cos_x>
        <cos_y>0.01</cos_y>
        <cos_z>0.01</cos_z>
    </Survey>
</root>